lence/THIRD-PARTY-LICENSES
lence/__init__.py
lence/cli.py
lence/version.py
lence/backend/__init__.py
lence/backend/app.py
lence/backend/config.py
lence/backend/database.py
lence/backend/pages.py
lence/backend/query_registry.py
lence/backend/sources.py
lence/backend/tests/test_app.py
lence/backend/tests/test_query_registry.py
lence/frontend/api.ts
lence/frontend/app.ts
lence/frontend/router.ts
lence/frontend/types.ts
lence/frontend/__tests__/api.test.ts
lence/frontend/__tests__/router.test.ts
lence/frontend/__tests__/types.test.ts
lence/frontend/components/__tests__/index.html
lence/frontend/components/area-chart/area-chart.ts
lence/frontend/components/chart/base-chart.ts
lence/frontend/components/chart/echarts-chart.html
lence/frontend/components/chart/echarts-chart.ts
lence/frontend/components/chart/__tests__/base-chart.test.ts
lence/frontend/components/checkbox/checkbox.ts
lence/frontend/components/data-table/data-table.ts
lence/frontend/components/dropdown/dropdown.ts
lence/frontend/components/gantt/echarts-gantt.ts
lence/frontend/components/layout/layout.html
lence/frontend/components/layout/layout.ts
lence/frontend/components/page/page.html
lence/frontend/components/page/page.ts
lence/frontend/markdoc/index.ts
lence/frontend/markdoc/__tests__/markdoc-golden.test.ts
lence/frontend/markdoc/__tests__/markdoc.test.ts
lence/frontend/markdoc/__tests__/golden/basic.html
lence/frontend/markdoc/__tests__/golden/basic.md
lence/frontend/markdoc/__tests__/golden/chart.html
lence/frontend/markdoc/__tests__/golden/chart.md
lence/frontend/markdoc/__tests__/golden/codeblock.html
lence/frontend/markdoc/__tests__/golden/codeblock.md
lence/frontend/markdoc/__tests__/golden/data.html
lence/frontend/markdoc/__tests__/golden/data.md
lence/frontend/markdoc/__tests__/golden/table.html
lence/frontend/markdoc/__tests__/golden/table.md
lence/frontend/stores/inputs.ts
lence/frontend/stores/__tests__/inputs.test.ts
lence/frontend/styles/theme.ts
lence/pages/index.md
lence-0.3.0.dist-info/METADATA
lence-0.3.0.dist-info/WHEEL
lence-0.3.0.dist-info/entry_points.txt
lence-0.3.0.dist-info/licenses/LICENSE
lence-0.3.0.dist-info/RECORD
