Metadata-Version: 2.4
Name: lence
Version: 0.3.0
Summary: A lightweight data visualization framework
Project-URL: Homepage, https://github.com/osks/lence
Project-URL: Documentation, https://github.com/osks/lence
Project-URL: Repository, https://github.com/osks/lence
Author-email: Oskar Skoog <oskar@osd.se>
License-Expression: MIT
License-File: LICENSE
Keywords: dashboard,data,duckdb,markdoc,visualization
Classifier: Development Status :: 3 - Alpha
Classifier: Framework :: FastAPI
Classifier: Intended Audience :: Developers
Classifier: License :: OSI Approved :: MIT License
Classifier: Programming Language :: Python :: 3
Classifier: Programming Language :: Python :: 3.11
Classifier: Programming Language :: Python :: 3.12
Requires-Python: >=3.11
Requires-Dist: click>=8.0
Requires-Dist: duckdb>=0.10.0
Requires-Dist: fastapi>=0.109.0
Requires-Dist: markdoc-py>=0.2.1
Requires-Dist: pydantic>=2.0
Requires-Dist: pyyaml>=6.0
Requires-Dist: uvicorn[standard]>=0.27.0
Provides-Extra: dev
Requires-Dist: httpx>=0.26.0; extra == 'dev'
Requires-Dist: pytest-asyncio>=0.23.0; extra == 'dev'
Requires-Dist: pytest-cov>=4.1.0; extra == 'dev'
Requires-Dist: pytest>=8.0.0; extra == 'dev'
Requires-Dist: ruff>=0.1.0; extra == 'dev'
